setup.py
firstpkg/__init__.py
firstpkg.egg-info/PKG-INFO
firstpkg.egg-info/SOURCES.txt
firstpkg.egg-info/dependency_links.txt
firstpkg.egg-info/not-zip-safe
firstpkg.egg-info/top_level.txt