Metadata-Version: 1.0
Name: firstpkg
Version: 0.1
Summary: This is my first package
Home-page: http://github.com/hoangdangninh
Author: hoang dang
Author-email: hoangdangninh@gmail.com
License: MIT
Platform: UNKNOWN
